ca_slack_block_kit/__init__.py
ca_slack_block_kit/emoji.py
ca_slack_block_kit-1.1.3.dist-info/WHEEL
ca_slack_block_kit-1.1.3.dist-info/METADATA
ca_slack_block_kit-1.1.3.dist-info/RECORD
