Metadata-Version: 2.3
Name: ca-slack-block-kit
Version: 1.1.3
Summary: A collection of simple, pre-configured Slack block kit components to use with Slack notification messages.
Author: Matthew Cane
Author-email: Matthew Cane <matthew.cane@citizensadvice.org.uk>
License:                                  Apache License
Requires-Python: >=3.10
Project-URL: Changelog, https://github.com/citizensadvice/ca-slack-block-kit/releases
Project-URL: Documentation, https://github.com/citizensadvice/ca-slack-block-kit/blob/main/docs.md
Project-URL: Homepage, https://github.com/citizensadvice/ca-slack-block-kit
Project-URL: Issues, https://github.com/citizensadvice/ca-slack-block-kit/issues
Project-URL: Repository, https://github.com/matthewcane/ca-slack-block-kit
